grott_ha_plugin-0.11.0.dist-info/METADATA
grott_ha_plugin-0.11.0.dist-info/WHEEL
grottext/__init__.py
grottext/ha/__init__.py
grottext/ha/__version__.py
grottext/ha/constants.py
grottext/ha/extension.py
grottext/ha/ha_types.py
grottext/ha/interface.py
grottext/ha/mappings.py
grottext/ha/mqtt.py
grott_ha_plugin-0.11.0.dist-info/RECORD
